request_factory/__init__.py
request_factory-2.dist-info/DESCRIPTION.rst
request_factory-2.dist-info/METADATA
request_factory-2.dist-info/RECORD
request_factory-2.dist-info/WHEEL
request_factory-2.dist-info/metadata.json
request_factory-2.dist-info/top_level.txt
