Metadata-Version: 2.0
Name: request-factory
Version: 2
Summary: Provide factory to do request: http
Home-page: https://github.com/tinyclues/request_factory
Author: Damien Goldenberg
Author-email: damien.goldenberg@tinyclues.com
License: UNKNOWN
Keywords: request,factory,http
Platform: UNKNOWN
Classifier: Development Status :: 2 - Pre-Alpha
Classifier: Natural Language :: English
Classifier: Programming Language :: Python :: 2.7
Requires-Dist: furl (>=0.4.95)
Requires-Dist: requests (>=2.7.0)
